image_helpers_system/__init__.py
image_helpers_system/image_ops.py
image_helpers_system-0.1.2.dist-info/METADATA
image_helpers_system-0.1.2.dist-info/WHEEL
image_helpers_system-0.1.2.dist-info/top_level.txt
image_helpers_system-0.1.2.dist-info/RECORD
