Metadata-Version: 2.1
Name: image-helpers-system
Version: 0.1.2
Summary: A simple image processing utility library
Classifier: Programming Language :: Python :: 3
Classifier: License :: OSI Approved :: MIT License
Classifier: Operating System :: OS Independent
Requires-Python: >=3.6
Requires-Dist: Pillow
